airscript.py
setup.py
airscript/__init__.py
airscript/__main__.py
airscript/gateway.py
airscript/session.py
airscript/anomalyshield/application.py
airscript/anomalyshield/rule.py
airscript/anomalyshield/traffic_matcher.py
airscript/anomalyshield/trigger.py
airscript/base/baseSettings-old.py
airscript/base/element.py
airscript/base/element_helpers.py
airscript/commands/__init__.py
airscript/declarative/__init__.py
airscript/declarative/basedoc.py
airscript/declarative/changelog.py
airscript/declarative/connecteddoc.py
airscript/declarative/defaults.py
airscript/declarative/envvalue.py
airscript/declarative/globaldoc.py
airscript/model/api_policy.py
airscript/model/backendgroup.py
airscript/model/baseObject.py
airscript/model/certificate.py
airscript/model/configuration.py
airscript/model/gateway.py
airscript/model/graphql.py
airscript/model/host.py
airscript/model/icap.py
airscript/model/iplist.py
airscript/model/jwks.py
airscript/model/kerberos.py
airscript/model/mapping.py
airscript/model/network_endpoint.py
airscript/model/node.py
airscript/model/openapi.py
airscript/model/route.py
airscript/model/template.py
airscript/model/validator.py
airscript/model/vhost.py
airscript/system_settings/anomalyshield.py
airscript/system_settings/default_route.py
airscript/system_settings/dynamic_ip_blacklist.py
airscript/system_settings/license.py
airscript/system_settings/log.py
airscript/system_settings/network_services.py
airscript/system_settings/reporting.py
airscript/system_settings/session.py
airscript/utils/cache.py
airscript/utils/cmdline.py
airscript/utils/completer.py
airscript/utils/console.py
airscript/utils/const.py
airscript/utils/internal.py
airscript/utils/keepalive.py
airscript/utils/output.py
airscript/utils/runinfo.py
airscript/utils/scripts.py
airscript/utils/templating.py
samples/config.yaml
samples/rc
samples/status-report.py
samples/sync-gw-config.py
samples/sync2env.py
samples/waf.pem
samples/__pycache__/status-report.cpython-312.pyc
pyAirscript-0.3.1.dist-info/COPYING
pyAirscript-0.3.1.dist-info/METADATA
pyAirscript-0.3.1.dist-info/WHEEL
pyAirscript-0.3.1.dist-info/entry_points.txt
pyAirscript-0.3.1.dist-info/top_level.txt
pyAirscript-0.3.1.dist-info/RECORD
