Metadata-Version: 2.1
Name: pyAirscript
Version: 0.3.1
Summary: Airlock Gateway Configuration Script Engine
Author-email: Urs Zurbuchen <info@airlock.com>
Project-URL: Official Website, https://www.airlock.com
Project-URL: Homepage, https://github.com/alalazu/airscript
Keywords: airlock
Classifier: License :: OSI Approved :: GNU General Public License v3 (GPLv3)
Classifier: Development Status :: 3 - Alpha
Classifier: Environment :: Console
Classifier: Programming Language :: Python
Classifier: Programming Language :: Python :: 3
Classifier: Intended Audience :: Developers
Classifier: Intended Audience :: Information Technology
Classifier: Intended Audience :: System Administrators
Classifier: Operating System :: Microsoft :: Windows
Classifier: Operating System :: POSIX :: Linux
Classifier: Topic :: System :: Systems Administration
Classifier: Topic :: Utilities
Requires-Python: >=3.11
License-File: COPYING
Requires-Dist: colorama
Requires-Dist: cryptography
Requires-Dist: pem
Requires-Dist: pyairlock
Requires-Dist: readline ; platform_system != "Windows"
Requires-Dist: pyreadline3 ; platform_system == "Windows"
Provides-Extra: doc
Requires-Dist: pdoc3 ; extra == 'doc'
